{"columnName": ["rpt_type", "upper_pri_girl_c6_c8_promotion_rate", "pri_c2_c6_current", "upper_pri_girl_c6_c8_current_rptr", "pri_girl_c1_c5_current_rptr", "secondary_boy_c9_c10_previous", "pri_girl_c2_c6_current", "secondary_c9_c10_repitition_rate", "pri_c1_c5_current_rptr", "pri_c1_c5_promotion_rate", "secondary_c10_c11_current_rptr", "secondary_girl_c10_c11_current", "pri_c2_c6_current_rptr", "secondary_girl_c9_c10_dropout_rate", "upper_pri_boy_c6_c8_dropout_rate", "upper_pri_girl_c6_c8_previous", "secondary_boy_c10_c11_current_rptr", "upper_pri_c7_c9_current_fresh", "upper_pri_c7_c9_current_rptr", "secondary_c9_c10_previous", "upper_pri_c6_c8_previous", "secondary_boy_c10_c11_current_fresh", "secondary_c9_c10_promotion_rate", "pri_girl_c1_c5_dropout_rate", "secondary_girl_c10_c11_current_fresh", "upper_pri_boy_c7_c9_current_fresh", "upper_pri_c6_c8_dropout_rate", "pri_boy_c2_c6_current", "secondary_c10_c11_current_fresh", "pri_boy_c2_c6_current_fresh", "secondary_girl_c10_c11_current_rptr", "upper_pri_girl_c6_c8_dropout_rate", "pri_c1_c5_repitition_rate", "secondary_c9_c10_current_rptr", "location_name", "pri_c2_c6_current_fresh", "upper_pri_c6_c8_current_rptr", "upper_pri_boy_c7_c9_current_rptr", "upper_pri_boy_c6_c8_repitition_rate", "upper_pri_girl_c7_c9_current_rptr", "pri_girl_c1_c5_repitition_rate", "pri_girl_c2_c6_current_rptr", "upper_pri_boy_c6_c8_current_rptr", "pri_boy_c1_c5_previous", "secondary_boy_c10_c11_current", "upper_pri_boy_c7_c9_current", "pri_boy_c1_c5_promotion_rate", "upper_pri_c6_c8_promotion_rate", "secondary_c10_c11_current", "secondary_girl_c9_c10_repitition_rate", "secondary_boy_c9_c10_repitition_rate", "secondary_girl_c9_c10_previous", "pri_boy_c2_c6_current_rptr", "secondary_girl_c9_c10_current_rptr", "pri_girl_c1_c5_previous", "secondary_c9_c10_dropout_rate", "secondary_boy_c9_c10_current_rptr", "location_code", "pri_boy_c1_c5_current_rptr", "secondary_girl_c9_c10_promotion_rate", "upper_pri_boy_c6_c8_promotion_rate", "secondary_boy_c9_c10_promotion_rate", "upper_pri_girl_c6_c8_repitition_rate", "upper_pri_girl_c7_c9_current_fresh", "pri_girl_c1_c5_promotion_rate", "pri_c1_c5_dropout_rate", "item_id", "item_name", "pri_girl_c2_c6_current_fresh", "upper_pri_c6_c8_repitition_rate", "pri_boy_c1_c5_dropout_rate", "pri_c1_c5_previous", "upper_pri_girl_c7_c9_current", "pri_boy_c1_c5_repitition_rate", "secondary_boy_c9_c10_dropout_rate", "upper_pri_boy_c6_c8_previous", "upper_pri_c7_c9_current"], "rowValue": [{"rpt_type": "D", "upper_pri_girl_c6_c8_promotion_rate": 93.79586390927285, "pri_c2_c6_current": 39367, "upper_pri_girl_c6_c8_current_rptr": 60, "pri_girl_c1_c5_current_rptr": 128, "secondary_boy_c9_c10_previous": 7148, "pri_girl_c2_c6_current": 19012, "secondary_c9_c10_repitition_rate": 1.7783353010625738, "pri_c1_c5_current_rptr": 260, "pri_c1_c5_promotion_rate": 92.06741520137467, "secondary_c10_c11_current_rptr": 195, "secondary_girl_c10_c11_current": 5572, "pri_c2_c6_current_rptr": 254, "secondary_girl_c9_c10_dropout_rate": 12.414116177389133, "upper_pri_boy_c6_c8_dropout_rate": 2.5869921661504827, "upper_pri_girl_c6_c8_previous": 10493, "secondary_boy_c10_c11_current_rptr": 108, "upper_pri_c7_c9_current_fresh": 20461, "upper_pri_c7_c9_current_rptr": 145, "secondary_c9_c10_previous": 13552, "upper_pri_c6_c8_previous": 21471, "secondary_boy_c10_c11_current_fresh": 6264, "secondary_c9_c10_promotion_rate": 86.6956906729634, "pri_girl_c1_c5_dropout_rate": 7.758328080298695, "secondary_girl_c10_c11_current_fresh": 5485, "upper_pri_boy_c7_c9_current_fresh": 10619, "upper_pri_c6_c8_dropout_rate": 4.075264309999534, "pri_boy_c2_c6_current": 20355, "secondary_c10_c11_current_fresh": 11749, "pri_boy_c2_c6_current_fresh": 20218, "secondary_girl_c10_c11_current_rptr": 87, "upper_pri_girl_c6_c8_dropout_rate": 5.6323263127799486, "pri_c1_c5_repitition_rate": 0.6120095096862275, "secondary_c9_c10_current_rptr": 241, "location_name": "JALAUN", "pri_c2_c6_current_fresh": 39113, "upper_pri_c6_c8_current_rptr": 135, "upper_pri_boy_c7_c9_current_rptr": 61, "upper_pri_boy_c6_c8_repitition_rate": 0.6831845509200218, "upper_pri_girl_c7_c9_current_rptr": 84, "pri_girl_c1_c5_repitition_rate": 0.6206662464238957, "pri_girl_c2_c6_current_rptr": 117, "upper_pri_boy_c6_c8_current_rptr": 75, "pri_boy_c1_c5_previous": 21860, "secondary_boy_c10_c11_current": 6372, "upper_pri_boy_c7_c9_current": 10680, "pri_boy_c1_c5_promotion_rate": 92.48856358645929, "upper_pri_c6_c8_promotion_rate": 95.2959806250291, "secondary_c10_c11_current": 11944, "secondary_girl_c9_c10_repitition_rate": 1.9362898188632105, "secondary_boy_c9_c10_repitition_rate": 1.6368214885282597, "secondary_girl_c9_c10_previous": 6404, "pri_boy_c2_c6_current_rptr": 137, "secondary_girl_c9_c10_current_rptr": 124, "pri_girl_c1_c5_previous": 20623, "secondary_c9_c10_dropout_rate": 11.525974025974026, "secondary_boy_c9_c10_current_rptr": 117, "location_code": "0935", "pri_boy_c1_c5_current_rptr": 132, "secondary_girl_c9_c10_promotion_rate": 85.64959400374765, "upper_pri_boy_c6_c8_promotion_rate": 96.7298232829295, "secondary_boy_c9_c10_promotion_rate": 87.6329043088976, "upper_pri_girl_c6_c8_repitition_rate": 0.5718097779472029, "upper_pri_girl_c7_c9_current_fresh": 9842, "pri_girl_c1_c5_promotion_rate": 91.62100567327741, "pri_c1_c5_dropout_rate": 7.320575288939105, "item_id": 1, "item_name": "General", "pri_girl_c2_c6_current_fresh": 18895, "upper_pri_c6_c8_repitition_rate": 0.6287550649713567, "pri_boy_c1_c5_dropout_rate": 6.907593778591034, "pri_c1_c5_previous": 42483, "upper_pri_girl_c7_c9_current": 9926, "pri_boy_c1_c5_repitition_rate": 0.6038426349496798, "secondary_boy_c9_c10_dropout_rate": 10.730274202574147, "upper_pri_boy_c6_c8_previous": 10978, "upper_pri_c7_c9_current": 20606}, {"rpt_type": "D", "upper_pri_girl_c6_c8_promotion_rate": 94.81517713646845, "pri_c2_c6_current": 64855, "upper_pri_girl_c6_c8_current_rptr": 49, "pri_girl_c1_c5_current_rptr": 94, "secondary_boy_c9_c10_previous": 7834, "pri_girl_c2_c6_current": 30840, "secondary_c9_c10_repitition_rate": 2.5955446556304924, "pri_c1_c5_current_rptr": 193, "pri_c1_c5_promotion_rate": 96.60039731736097, "secondary_c10_c11_current_rptr": 363, "secondary_girl_c10_c11_current": 6001, "pri_c2_c6_current_rptr": 182, "secondary_girl_c9_c10_dropout_rate": 12.096420745069393, "upper_pri_boy_c6_c8_dropout_rate": 4.276189255032697, "upper_pri_girl_c6_c8_previous": 14311, "secondary_boy_c10_c11_current_rptr": 246, "upper_pri_c7_c9_current_fresh": 28451, "upper_pri_c7_c9_current_rptr": 121, "secondary_c9_c10_previous": 14679, "upper_pri_c6_c8_previous": 29909, "secondary_boy_c10_c11_current_fresh": 7360, "secondary_c9_c10_promotion_rate": 90.22412970910825, "pri_girl_c1_c5_dropout_rate": 2.9915067631330605, "secondary_girl_c10_c11_current_fresh": 5884, "upper_pri_boy_c7_c9_current_fresh": 14882, "upper_pri_c6_c8_dropout_rate": 4.547126283058611, "pri_boy_c2_c6_current": 34015, "secondary_c10_c11_current_fresh": 13244, "pri_boy_c2_c6_current_fresh": 33928, "secondary_girl_c10_c11_current_rptr": 117, "upper_pri_girl_c6_c8_dropout_rate": 4.842428900845504, "pri_c1_c5_repitition_rate": 0.2882791378512002, "secondary_c9_c10_current_rptr": 381, "location_name": "JALAUN", "pri_c2_c6_current_fresh": 64673, "upper_pri_c6_c8_current_rptr": 98, "upper_pri_boy_c7_c9_current_rptr": 61, "upper_pri_boy_c6_c8_repitition_rate": 0.31414283882549043, "upper_pri_girl_c7_c9_current_rptr": 60, "pri_girl_c1_c5_repitition_rate": 0.2956904687008493, "pri_girl_c2_c6_current_rptr": 95, "upper_pri_boy_c6_c8_current_rptr": 49, "pri_boy_c1_c5_previous": 35159, "secondary_boy_c10_c11_current": 7606, "upper_pri_boy_c7_c9_current": 14943, "pri_boy_c1_c5_promotion_rate": 96.49876276344605, "upper_pri_c6_c8_promotion_rate": 95.12521314654452, "secondary_c10_c11_current": 13607, "secondary_girl_c9_c10_repitition_rate": 1.9430241051862673, "secondary_boy_c9_c10_repitition_rate": 3.165688026550932, "secondary_girl_c9_c10_previous": 6845, "pri_boy_c2_c6_current_rptr": 87, "secondary_girl_c9_c10_current_rptr": 133, "pri_girl_c1_c5_previous": 31790, "secondary_c9_c10_dropout_rate": 7.180325635261258, "secondary_boy_c9_c10_current_rptr": 248, "location_code": "0935", "pri_boy_c1_c5_current_rptr": 99, "secondary_girl_c9_c10_promotion_rate": 85.96055514974434, "upper_pri_boy_c6_c8_promotion_rate": 95.40966790614182, "secondary_boy_c9_c10_promotion_rate": 93.94945111054378, "upper_pri_girl_c6_c8_repitition_rate": 0.3423939626860457, "upper_pri_girl_c7_c9_current_fresh": 13569, "pri_girl_c1_c5_promotion_rate": 96.71280276816609, "pri_c1_c5_dropout_rate": 3.1113235447878234, "item_id": 2, "item_name": "SC", "pri_girl_c2_c6_current_fresh": 30745, "upper_pri_c6_c8_repitition_rate": 0.3276605703968705, "pri_boy_c1_c5_dropout_rate": 3.2196592622088227, "pri_c1_c5_previous": 66949, "upper_pri_girl_c7_c9_current": 13629, "pri_boy_c1_c5_repitition_rate": 0.2815779743451179, "secondary_boy_c9_c10_dropout_rate": 2.8848608629052848, "upper_pri_boy_c6_c8_previous": 15598, "upper_pri_c7_c9_current": 28572}, {"rpt_type": "D", "upper_pri_girl_c6_c8_promotion_rate": -1.1235955056179776, "pri_c2_c6_current": 0, "upper_pri_girl_c6_c8_current_rptr": 0, "pri_girl_c1_c5_current_rptr": 0, "secondary_boy_c9_c10_previous": 80, "pri_girl_c2_c6_current": 0, "secondary_c9_c10_repitition_rate": 7.6923076923076925, "pri_c1_c5_current_rptr": 2, "pri_c1_c5_promotion_rate": -0.234192037470726, "secondary_c10_c11_current_rptr": 6, "secondary_girl_c10_c11_current": 0, "pri_c2_c6_current_rptr": 2, "secondary_girl_c9_c10_dropout_rate": 100.0, "upper_pri_boy_c6_c8_dropout_rate": 101.16731517509727, "upper_pri_girl_c6_c8_previous": 178, "secondary_boy_c10_c11_current_rptr": 2, "upper_pri_c7_c9_current_fresh": -5, "upper_pri_c7_c9_current_rptr": 5, "secondary_c9_c10_previous": 104, "upper_pri_c6_c8_previous": 435, "secondary_boy_c10_c11_current_fresh": -2, "secondary_c9_c10_promotion_rate": -5.769230769230769, "pri_girl_c1_c5_dropout_rate": 100.0, "secondary_girl_c10_c11_current_fresh": -4, "upper_pri_boy_c7_c9_current_fresh": -3, "upper_pri_c6_c8_dropout_rate": 101.14942528735632, "pri_boy_c2_c6_current": 0, "secondary_c10_c11_current_fresh": -6, "pri_boy_c2_c6_current_fresh": -2, "secondary_girl_c10_c11_current_rptr": 4, "upper_pri_girl_c6_c8_dropout_rate": 101.12359550561797, "pri_c1_c5_repitition_rate": 0.234192037470726, "secondary_c9_c10_current_rptr": 8, "location_name": "JALAUN", "pri_c2_c6_current_fresh": -2, "upper_pri_c6_c8_current_rptr": 0, "upper_pri_boy_c7_c9_current_rptr": 3, "upper_pri_boy_c6_c8_repitition_rate": 0.0, "upper_pri_girl_c7_c9_current_rptr": 2, "pri_girl_c1_c5_repitition_rate": 0.0, "pri_girl_c2_c6_current_rptr": 0, "upper_pri_boy_c6_c8_current_rptr": 0, "pri_boy_c1_c5_previous": 416, "secondary_boy_c10_c11_current": 0, "upper_pri_boy_c7_c9_current": 0, "pri_boy_c1_c5_promotion_rate": -0.4807692307692308, "upper_pri_c6_c8_promotion_rate": -1.1494252873563218, "secondary_c10_c11_current": 0, "secondary_girl_c9_c10_repitition_rate": 16.666666666666668, "secondary_boy_c9_c10_repitition_rate": 5.0, "secondary_girl_c9_c10_previous": 24, "pri_boy_c2_c6_current_rptr": 2, "secondary_girl_c9_c10_current_rptr": 4, "pri_girl_c1_c5_previous": 438, "secondary_c9_c10_dropout_rate": 98.07692307692308, "secondary_boy_c9_c10_current_rptr": 4, "location_code": "0935", "pri_boy_c1_c5_current_rptr": 2, "secondary_girl_c9_c10_promotion_rate": -16.666666666666668, "upper_pri_boy_c6_c8_promotion_rate": -1.1673151750972763, "secondary_boy_c9_c10_promotion_rate": -2.5, "upper_pri_girl_c6_c8_repitition_rate": 0.0, "upper_pri_girl_c7_c9_current_fresh": -2, "pri_girl_c1_c5_promotion_rate": 0.0, "pri_c1_c5_dropout_rate": 100.0, "item_id": 3, "item_name": "ST", "pri_girl_c2_c6_current_fresh": 0, "upper_pri_c6_c8_repitition_rate": 0.0, "pri_boy_c1_c5_dropout_rate": 100.0, "pri_c1_c5_previous": 854, "upper_pri_girl_c7_c9_current": 0, "pri_boy_c1_c5_repitition_rate": 0.4807692307692308, "secondary_boy_c9_c10_dropout_rate": 97.5, "upper_pri_boy_c6_c8_previous": 257, "upper_pri_c7_c9_current": 0}, {"rpt_type": "D", "upper_pri_girl_c6_c8_promotion_rate": 97.14856429463171, "pri_c2_c6_current": 81062, "upper_pri_girl_c6_c8_current_rptr": 49, "pri_girl_c1_c5_current_rptr": 135, "secondary_boy_c9_c10_previous": 12476, "pri_girl_c2_c6_current": 39137, "secondary_c9_c10_repitition_rate": 2.0867768595041323, "pri_c1_c5_current_rptr": 260, "pri_c1_c5_promotion_rate": 97.47171358953946, "secondary_c10_c11_current_rptr": 479, "secondary_girl_c10_c11_current": 10993, "pri_c2_c6_current_rptr": 256, "secondary_girl_c9_c10_dropout_rate": 6.200955305356533, "upper_pri_boy_c6_c8_dropout_rate": 0.0, "upper_pri_girl_c6_c8_previous": 20025, "secondary_boy_c10_c11_current_rptr": 303, "upper_pri_c7_c9_current_fresh": 39805, "upper_pri_c7_c9_current_rptr": 139, "secondary_c9_c10_previous": 24200, "upper_pri_c6_c8_previous": 40359, "secondary_boy_c10_c11_current_fresh": 12176, "secondary_c9_c10_promotion_rate": 95.01239669421487, "pri_girl_c1_c5_dropout_rate": 2.454828660436137, "secondary_girl_c10_c11_current_fresh": 10817, "upper_pri_boy_c7_c9_current_fresh": 20351, "upper_pri_c6_c8_dropout_rate": 1.1125151762927723, "pri_boy_c2_c6_current": 41925, "secondary_c10_c11_current_fresh": 22993, "pri_boy_c2_c6_current_fresh": 41801, "secondary_girl_c10_c11_current_rptr": 176, "upper_pri_girl_c6_c8_dropout_rate": 2.606741573033708, "pri_c1_c5_repitition_rate": 0.31362331427468576, "secondary_c9_c10_current_rptr": 505, "location_name": "JALAUN", "pri_c2_c6_current_fresh": 80806, "upper_pri_c6_c8_current_rptr": 105, "upper_pri_boy_c7_c9_current_rptr": 77, "upper_pri_boy_c6_c8_repitition_rate": 0.0, "upper_pri_girl_c7_c9_current_rptr": 62, "pri_girl_c1_c5_repitition_rate": 0.3364485981308411, "pri_girl_c2_c6_current_rptr": 132, "upper_pri_boy_c6_c8_current_rptr": 56, "pri_boy_c1_c5_previous": 42777, "secondary_boy_c10_c11_current": 12479, "upper_pri_boy_c7_c9_current": 20428, "pri_boy_c1_c5_promotion_rate": 97.71840007480655, "upper_pri_c6_c8_promotion_rate": 98.62731980475235, "secondary_c10_c11_current": 23472, "secondary_girl_c9_c10_repitition_rate": 1.5353121801432958, "secondary_boy_c9_c10_repitition_rate": 2.4046168643796086, "secondary_girl_c9_c10_previous": 11724, "pri_boy_c2_c6_current_rptr": 124, "secondary_girl_c9_c10_current_rptr": 180, "pri_girl_c1_c5_previous": 40125, "secondary_c9_c10_dropout_rate": 2.9008264462809916, "secondary_boy_c9_c10_current_rptr": 325, "location_code": "0935", "pri_boy_c1_c5_current_rptr": 125, "secondary_girl_c9_c10_promotion_rate": 92.26373251450018, "upper_pri_boy_c6_c8_promotion_rate": 100.0, "secondary_boy_c9_c10_promotion_rate": 97.5953831356204, "upper_pri_girl_c6_c8_repitition_rate": 0.24469413233458176, "upper_pri_girl_c7_c9_current_fresh": 19454, "pri_girl_c1_c5_promotion_rate": 97.20872274143302, "pri_c1_c5_dropout_rate": 2.214663096185858, "item_id": 4, "item_name": "OBC", "pri_girl_c2_c6_current_fresh": 39005, "upper_pri_c6_c8_repitition_rate": 0.26016501895488, "pri_boy_c1_c5_dropout_rate": 1.9893868200201044, "pri_c1_c5_previous": 82902, "upper_pri_girl_c7_c9_current": 19516, "pri_boy_c1_c5_repitition_rate": 0.2922131051733408, "secondary_boy_c9_c10_dropout_rate": 0.0, "upper_pri_boy_c6_c8_previous": 20334, "upper_pri_c7_c9_current": 39944}, {"rpt_type": "D", "upper_pri_girl_c6_c8_promotion_rate": 95.23629657608817, "pri_c2_c6_current": 185284, "upper_pri_girl_c6_c8_current_rptr": 158, "pri_girl_c1_c5_current_rptr": 357, "secondary_boy_c9_c10_previous": 27538, "pri_girl_c2_c6_current": 88989, "secondary_c9_c10_repitition_rate": 2.1604644522699155, "pri_c1_c5_current_rptr": 715, "pri_c1_c5_promotion_rate": 95.54941300701907, "secondary_c10_c11_current_rptr": 1043, "secondary_girl_c10_c11_current": 22566, "pri_c2_c6_current_rptr": 694, "secondary_girl_c9_c10_dropout_rate": 9.497139656758812, "upper_pri_boy_c6_c8_dropout_rate": 2.41270379714631, "upper_pri_girl_c6_c8_previous": 45007, "secondary_boy_c10_c11_current_rptr": 659, "upper_pri_c7_c9_current_fresh": 88712, "upper_pri_c7_c9_current_rptr": 410, "secondary_c9_c10_previous": 52535, "upper_pri_c6_c8_previous": 92174, "secondary_boy_c10_c11_current_fresh": 25798, "secondary_c9_c10_promotion_rate": 91.329589797278, "pri_girl_c1_c5_dropout_rate": 4.274221304422647, "secondary_girl_c10_c11_current_fresh": 22182, "upper_pri_boy_c7_c9_current_fresh": 45849, "upper_pri_c6_c8_dropout_rate": 3.389242085620674, "pri_boy_c2_c6_current": 96295, "secondary_c10_c11_current_fresh": 47980, "pri_boy_c2_c6_current_fresh": 95945, "secondary_girl_c10_c11_current_rptr": 384, "upper_pri_girl_c6_c8_dropout_rate": 4.412646921589975, "pri_c1_c5_repitition_rate": 0.37010580367310597, "secondary_c9_c10_current_rptr": 1135, "location_name": "JALAUN", "pri_c2_c6_current_fresh": 184590, "upper_pri_c6_c8_current_rptr": 338, "upper_pri_boy_c7_c9_current_rptr": 202, "upper_pri_boy_c6_c8_repitition_rate": 0.38162274471558505, "upper_pri_girl_c7_c9_current_rptr": 208, "pri_girl_c1_c5_repitition_rate": 0.3839700567888487, "pri_girl_c2_c6_current_rptr": 344, "upper_pri_boy_c6_c8_current_rptr": 180, "pri_boy_c1_c5_previous": 100212, "secondary_boy_c10_c11_current": 26457, "upper_pri_boy_c7_c9_current": 46051, "pri_boy_c1_c5_promotion_rate": 95.74202690296572, "upper_pri_c6_c8_promotion_rate": 96.24406014711307, "secondary_c10_c11_current": 49023, "secondary_girl_c9_c10_repitition_rate": 1.7642117054046487, "secondary_boy_c9_c10_repitition_rate": 2.520153969060934, "secondary_girl_c9_c10_previous": 24997, "pri_boy_c2_c6_current_rptr": 350, "secondary_girl_c9_c10_current_rptr": 441, "pri_girl_c1_c5_previous": 92976, "secondary_c9_c10_dropout_rate": 6.509945750452079, "secondary_boy_c9_c10_current_rptr": 694, "location_code": "0935", "pri_boy_c1_c5_current_rptr": 358, "secondary_girl_c9_c10_promotion_rate": 88.73864863783653, "upper_pri_boy_c6_c8_promotion_rate": 97.20567345813811, "secondary_boy_c9_c10_promotion_rate": 93.68145834846393, "upper_pri_girl_c6_c8_repitition_rate": 0.35105650232186103, "upper_pri_girl_c7_c9_current_fresh": 42863, "pri_girl_c1_c5_promotion_rate": 95.3418086387885, "pri_c1_c5_dropout_rate": 4.080481189307824, "item_id": 6, "item_name": "Overall", "pri_girl_c2_c6_current_fresh": 88645, "upper_pri_c6_c8_repitition_rate": 0.3666977672662573, "pri_boy_c1_c5_dropout_rate": 3.900730451442941, "pri_c1_c5_previous": 193188, "upper_pri_girl_c7_c9_current": 43071, "pri_boy_c1_c5_repitition_rate": 0.35724264559134633, "secondary_boy_c9_c10_dropout_rate": 3.7983876824751253, "upper_pri_boy_c6_c8_previous": 47167, "upper_pri_c7_c9_current": 89122}], "staticFilter": null, "columnView": null, "columnDataType": null, "msData": null, "status": "1", "errorMessage": null, "jsonString": null, "yearList": ["2014-15", "2015-16", "2016-17", "2017-18", "2018-19"]}