{"columnName": ["rpt_type", "upper_pri_girl_c6_c8_promotion_rate", "pri_c2_c6_current", "upper_pri_girl_c6_c8_current_rptr", "pri_girl_c1_c5_current_rptr", "secondary_boy_c9_c10_previous", "pri_girl_c2_c6_current", "secondary_c9_c10_repitition_rate", "pri_c1_c5_current_rptr", "pri_c1_c5_promotion_rate", "secondary_c10_c11_current_rptr", "secondary_girl_c10_c11_current", "pri_c2_c6_current_rptr", "secondary_girl_c9_c10_dropout_rate", "upper_pri_boy_c6_c8_dropout_rate", "upper_pri_girl_c6_c8_previous", "secondary_boy_c10_c11_current_rptr", "upper_pri_c7_c9_current_fresh", "upper_pri_c7_c9_current_rptr", "secondary_c9_c10_previous", "upper_pri_c6_c8_previous", "secondary_boy_c10_c11_current_fresh", "secondary_c9_c10_promotion_rate", "pri_girl_c1_c5_dropout_rate", "secondary_girl_c10_c11_current_fresh", "upper_pri_boy_c7_c9_current_fresh", "upper_pri_c6_c8_dropout_rate", "pri_boy_c2_c6_current", "secondary_c10_c11_current_fresh", "pri_boy_c2_c6_current_fresh", "secondary_girl_c10_c11_current_rptr", "upper_pri_girl_c6_c8_dropout_rate", "pri_c1_c5_repitition_rate", "secondary_c9_c10_current_rptr", "location_name", "pri_c2_c6_current_fresh", "upper_pri_c6_c8_current_rptr", "upper_pri_boy_c7_c9_current_rptr", "upper_pri_boy_c6_c8_repitition_rate", "upper_pri_girl_c7_c9_current_rptr", "pri_girl_c1_c5_repitition_rate", "pri_girl_c2_c6_current_rptr", "upper_pri_boy_c6_c8_current_rptr", "pri_boy_c1_c5_previous", "secondary_boy_c10_c11_current", "upper_pri_boy_c7_c9_current", "pri_boy_c1_c5_promotion_rate", "upper_pri_c6_c8_promotion_rate", "secondary_c10_c11_current", "secondary_girl_c9_c10_repitition_rate", "secondary_boy_c9_c10_repitition_rate", "secondary_girl_c9_c10_previous", "pri_boy_c2_c6_current_rptr", "secondary_girl_c9_c10_current_rptr", "pri_girl_c1_c5_previous", "secondary_c9_c10_dropout_rate", "secondary_boy_c9_c10_current_rptr", "location_code", "pri_boy_c1_c5_current_rptr", "secondary_girl_c9_c10_promotion_rate", "upper_pri_boy_c6_c8_promotion_rate", "secondary_boy_c9_c10_promotion_rate", "upper_pri_girl_c6_c8_repitition_rate", "upper_pri_girl_c7_c9_current_fresh", "pri_girl_c1_c5_promotion_rate", "pri_c1_c5_dropout_rate", "item_id", "item_name", "pri_girl_c2_c6_current_fresh", "upper_pri_c6_c8_repitition_rate", "pri_boy_c1_c5_dropout_rate", "pri_c1_c5_previous", "upper_pri_girl_c7_c9_current", "pri_boy_c1_c5_repitition_rate", "secondary_boy_c9_c10_dropout_rate", "upper_pri_boy_c6_c8_previous", "upper_pri_c7_c9_current"], "rowValue": [{"rpt_type": "D", "upper_pri_girl_c6_c8_promotion_rate": 92.39100630655334, "pri_c2_c6_current": 26863, "upper_pri_girl_c6_c8_current_rptr": 266, "pri_girl_c1_c5_current_rptr": 323, "secondary_boy_c9_c10_previous": 5304, "pri_girl_c2_c6_current": 12586, "secondary_c9_c10_repitition_rate": 8.710234779957313, "pri_c1_c5_current_rptr": 766, "pri_c1_c5_promotion_rate": 92.39326199809302, "secondary_c10_c11_current_rptr": 541, "secondary_girl_c10_c11_current": 3415, "pri_c2_c6_current_rptr": 700, "secondary_girl_c9_c10_dropout_rate": 21.808158765159867, "upper_pri_boy_c6_c8_dropout_rate": 4.100418410041841, "upper_pri_girl_c6_c8_previous": 7294, "secondary_boy_c10_c11_current_rptr": 318, "upper_pri_c7_c9_current_fresh": 14562, "upper_pri_c7_c9_current_rptr": 817, "secondary_c9_c10_previous": 9839, "upper_pri_c6_c8_previous": 15659, "secondary_boy_c10_c11_current_fresh": 3446, "secondary_c9_c10_promotion_rate": 67.46620591523529, "pri_girl_c1_c5_dropout_rate": 5.619240278714318, "secondary_girl_c10_c11_current_fresh": 3192, "upper_pri_boy_c7_c9_current_fresh": 7823, "upper_pri_c6_c8_dropout_rate": 4.036017625646593, "pri_boy_c2_c6_current": 14277, "secondary_c10_c11_current_fresh": 6638, "pri_boy_c2_c6_current_fresh": 13889, "secondary_girl_c10_c11_current_rptr": 223, "upper_pri_girl_c6_c8_dropout_rate": 3.962160680010968, "pri_c1_c5_repitition_rate": 2.70508881590564, "secondary_c9_c10_current_rptr": 857, "location_name": "CHITTAURGARH", "pri_c2_c6_current_fresh": 26163, "upper_pri_c6_c8_current_rptr": 465, "upper_pri_boy_c7_c9_current_rptr": 449, "upper_pri_boy_c6_c8_repitition_rate": 2.3789599521817095, "upper_pri_girl_c7_c9_current_rptr": 368, "pri_girl_c1_c5_repitition_rate": 2.420019480032966, "pri_girl_c2_c6_current_rptr": 312, "upper_pri_boy_c6_c8_current_rptr": 199, "pri_boy_c1_c5_previous": 14970, "secondary_boy_c10_c11_current": 3764, "upper_pri_boy_c7_c9_current": 8272, "pri_boy_c1_c5_promotion_rate": 92.77889111556446, "upper_pri_c6_c8_promotion_rate": 92.9944440896609, "secondary_c10_c11_current": 7179, "secondary_girl_c9_c10_repitition_rate": 7.805953693495039, "secondary_boy_c9_c10_repitition_rate": 9.48340874811463, "secondary_girl_c9_c10_previous": 4535, "pri_boy_c2_c6_current_rptr": 388, "secondary_girl_c9_c10_current_rptr": 354, "pri_girl_c1_c5_previous": 13347, "secondary_c9_c10_dropout_rate": 23.8235593048074, "secondary_boy_c9_c10_current_rptr": 503, "location_code": "0829", "pri_boy_c1_c5_current_rptr": 443, "secondary_girl_c9_c10_promotion_rate": 70.3858875413451, "upper_pri_boy_c6_c8_promotion_rate": 93.52062163777644, "secondary_boy_c9_c10_promotion_rate": 64.96983408748115, "upper_pri_girl_c6_c8_repitition_rate": 3.6468330134357005, "upper_pri_girl_c7_c9_current_fresh": 6739, "pri_girl_c1_c5_promotion_rate": 91.96074024125272, "pri_c1_c5_dropout_rate": 4.901649186001342, "item_id": 1, "item_name": "General", "pri_girl_c2_c6_current_fresh": 12274, "upper_pri_c6_c8_repitition_rate": 2.969538284692509, "pri_boy_c1_c5_dropout_rate": 4.261857047428189, "pri_c1_c5_previous": 28317, "upper_pri_girl_c7_c9_current": 7107, "pri_boy_c1_c5_repitition_rate": 2.959251837007348, "secondary_boy_c9_c10_dropout_rate": 25.546757164404223, "upper_pri_boy_c6_c8_previous": 8365, "upper_pri_c7_c9_current": 15379}, {"rpt_type": "D", "upper_pri_girl_c6_c8_promotion_rate": 86.42058923129021, "pri_c2_c6_current": 26843, "upper_pri_girl_c6_c8_current_rptr": 67, "pri_girl_c1_c5_current_rptr": 309, "secondary_boy_c9_c10_previous": 4429, "pri_girl_c2_c6_current": 12498, "secondary_c9_c10_repitition_rate": 11.532258064516128, "pri_c1_c5_current_rptr": 669, "pri_c1_c5_promotion_rate": 89.83507121924623, "secondary_c10_c11_current_rptr": 395, "secondary_girl_c10_c11_current": 1810, "pri_c2_c6_current_rptr": 480, "secondary_girl_c9_c10_dropout_rate": 34.407173696446364, "upper_pri_boy_c6_c8_dropout_rate": 9.070444915254237, "upper_pri_girl_c6_c8_previous": 5906, "secondary_boy_c10_c11_current_rptr": 268, "upper_pri_c7_c9_current_fresh": 11871, "upper_pri_c7_c9_current_rptr": 676, "secondary_c9_c10_previous": 7440, "upper_pri_c6_c8_previous": 13458, "secondary_boy_c10_c11_current_fresh": 2242, "secondary_c9_c10_promotion_rate": 52.755376344086024, "pri_girl_c1_c5_dropout_rate": 8.511874500689956, "secondary_girl_c10_c11_current_fresh": 1683, "upper_pri_boy_c7_c9_current_fresh": 6767, "upper_pri_c6_c8_dropout_rate": 10.551344924951701, "pri_boy_c2_c6_current": 14345, "secondary_c10_c11_current_fresh": 3925, "pri_boy_c2_c6_current_fresh": 14075, "secondary_girl_c10_c11_current_rptr": 127, "upper_pri_girl_c6_c8_dropout_rate": 12.444971215712835, "pri_c1_c5_repitition_rate": 2.279697403393989, "secondary_c9_c10_current_rptr": 858, "location_name": "CHITTAURGARH", "pri_c2_c6_current_fresh": 26363, "upper_pri_c6_c8_current_rptr": 167, "upper_pri_boy_c7_c9_current_rptr": 442, "upper_pri_boy_c6_c8_repitition_rate": 1.3241525423728815, "upper_pri_girl_c7_c9_current_rptr": 234, "pri_girl_c1_c5_repitition_rate": 2.2441716900283244, "pri_girl_c2_c6_current_rptr": 210, "upper_pri_boy_c6_c8_current_rptr": 100, "pri_boy_c1_c5_previous": 15577, "secondary_boy_c10_c11_current": 2510, "upper_pri_boy_c7_c9_current": 7209, "pri_boy_c1_c5_promotion_rate": 90.35757848109392, "upper_pri_c6_c8_promotion_rate": 88.20775746767721, "secondary_c10_c11_current": 4320, "secondary_girl_c9_c10_repitition_rate": 9.697774825639323, "secondary_boy_c9_c10_repitition_rate": 12.779408444344096, "secondary_girl_c9_c10_previous": 3011, "pri_boy_c2_c6_current_rptr": 270, "secondary_girl_c9_c10_current_rptr": 292, "pri_girl_c1_c5_previous": 13769, "secondary_c9_c10_dropout_rate": 35.71236559139785, "secondary_boy_c9_c10_current_rptr": 566, "location_code": "0829", "pri_boy_c1_c5_current_rptr": 360, "secondary_girl_c9_c10_promotion_rate": 55.895051477914315, "upper_pri_boy_c6_c8_promotion_rate": 89.60540254237289, "secondary_boy_c9_c10_promotion_rate": 50.62090765409799, "upper_pri_girl_c6_c8_repitition_rate": 1.1344395529969522, "upper_pri_girl_c7_c9_current_fresh": 5104, "pri_girl_c1_c5_promotion_rate": 89.24395380928172, "pri_c1_c5_dropout_rate": 7.885231377359776, "item_id": 2, "item_name": "SC", "pri_girl_c2_c6_current_fresh": 12288, "upper_pri_c6_c8_repitition_rate": 1.2408976073710805, "pri_boy_c1_c5_dropout_rate": 7.331321820632985, "pri_c1_c5_previous": 29346, "upper_pri_girl_c7_c9_current": 5338, "pri_boy_c1_c5_repitition_rate": 2.311099698273095, "secondary_boy_c9_c10_dropout_rate": 36.59968390155792, "upper_pri_boy_c6_c8_previous": 7552, "upper_pri_c7_c9_current": 12547}, {"rpt_type": "D", "upper_pri_girl_c6_c8_promotion_rate": 80.87735557615076, "pri_c2_c6_current": 23486, "upper_pri_girl_c6_c8_current_rptr": 10, "pri_girl_c1_c5_current_rptr": 390, "secondary_boy_c9_c10_previous": 1925, "pri_girl_c2_c6_current": 10519, "secondary_c9_c10_repitition_rate": 12.839586028460543, "pri_c1_c5_current_rptr": 837, "pri_c1_c5_promotion_rate": 84.36189775652814, "secondary_c10_c11_current_rptr": 148, "secondary_girl_c10_c11_current": 638, "pri_c2_c6_current_rptr": 548, "secondary_girl_c9_c10_dropout_rate": 38.389031705227076, "upper_pri_boy_c6_c8_dropout_rate": 18.739967897271267, "upper_pri_girl_c6_c8_previous": 3237, "secondary_boy_c10_c11_current_rptr": 101, "upper_pri_c7_c9_current_fresh": 6633, "upper_pri_c7_c9_current_rptr": 301, "secondary_c9_c10_previous": 3092, "upper_pri_c6_c8_previous": 8221, "secondary_boy_c10_c11_current_fresh": 834, "secondary_c9_c10_promotion_rate": 46.08667529107374, "pri_girl_c1_c5_dropout_rate": 14.14783238156519, "secondary_girl_c10_c11_current_fresh": 591, "upper_pri_boy_c7_c9_current_fresh": 4015, "upper_pri_c6_c8_dropout_rate": 18.769006203624862, "pri_boy_c2_c6_current": 12967, "secondary_c10_c11_current_fresh": 1425, "pri_boy_c2_c6_current_fresh": 12654, "secondary_girl_c10_c11_current_rptr": 47, "upper_pri_girl_c6_c8_dropout_rate": 18.81371640407785, "pri_c1_c5_repitition_rate": 3.078337624126517, "secondary_c9_c10_current_rptr": 397, "location_name": "CHITTAURGARH", "pri_c2_c6_current_fresh": 22938, "upper_pri_c6_c8_current_rptr": 45, "upper_pri_boy_c7_c9_current_rptr": 209, "upper_pri_boy_c6_c8_repitition_rate": 0.702247191011236, "upper_pri_girl_c7_c9_current_rptr": 92, "pri_girl_c1_c5_repitition_rate": 3.136813319391941, "pri_girl_c2_c6_current_rptr": 235, "upper_pri_boy_c6_c8_current_rptr": 35, "pri_boy_c1_c5_previous": 14757, "secondary_boy_c10_c11_current": 935, "upper_pri_boy_c7_c9_current": 4224, "pri_boy_c1_c5_promotion_rate": 85.74913600325269, "upper_pri_c6_c8_promotion_rate": 80.68361513197908, "secondary_c10_c11_current": 1573, "secondary_girl_c9_c10_repitition_rate": 10.968294772922022, "secondary_boy_c9_c10_repitition_rate": 13.974025974025974, "secondary_girl_c9_c10_previous": 1167, "pri_boy_c2_c6_current_rptr": 313, "secondary_girl_c9_c10_current_rptr": 128, "pri_girl_c1_c5_previous": 12433, "secondary_c9_c10_dropout_rate": 41.073738680465716, "secondary_boy_c9_c10_current_rptr": 269, "location_code": "0829", "pri_boy_c1_c5_current_rptr": 447, "secondary_girl_c9_c10_promotion_rate": 50.6426735218509, "upper_pri_boy_c6_c8_promotion_rate": 80.55778491171749, "secondary_boy_c9_c10_promotion_rate": 43.324675324675326, "upper_pri_girl_c6_c8_repitition_rate": 0.3089280197713933, "upper_pri_girl_c7_c9_current_fresh": 2618, "pri_girl_c1_c5_promotion_rate": 82.71535429904287, "pri_c1_c5_dropout_rate": 12.559764619345348, "item_id": 3, "item_name": "ST", "pri_girl_c2_c6_current_fresh": 10284, "upper_pri_c6_c8_repitition_rate": 0.5473786643960589, "pri_boy_c1_c5_dropout_rate": 11.22179304736735, "pri_c1_c5_previous": 27190, "upper_pri_girl_c7_c9_current": 2710, "pri_boy_c1_c5_repitition_rate": 3.0290709493799555, "secondary_boy_c9_c10_dropout_rate": 42.701298701298704, "upper_pri_boy_c6_c8_previous": 4984, "upper_pri_c7_c9_current": 6934}, {"rpt_type": "D", "upper_pri_girl_c6_c8_promotion_rate": 90.58697208303508, "pri_c2_c6_current": 70955, "upper_pri_girl_c6_c8_current_rptr": 153, "pri_girl_c1_c5_current_rptr": 723, "secondary_boy_c9_c10_previous": 12009, "pri_girl_c2_c6_current": 33907, "secondary_c9_c10_repitition_rate": 10.158619660882104, "pri_c1_c5_current_rptr": 1466, "pri_c1_c5_promotion_rate": 92.29792468552836, "secondary_c10_c11_current_rptr": 1050, "secondary_girl_c10_c11_current": 5646, "pri_c2_c6_current_rptr": 1175, "secondary_girl_c9_c10_dropout_rate": 26.943964453221426, "upper_pri_boy_c6_c8_dropout_rate": 6.484896819858439, "upper_pri_girl_c6_c8_previous": 16764, "secondary_boy_c10_c11_current_rptr": 721, "upper_pri_c7_c9_current_fresh": 33647, "upper_pri_c7_c9_current_rptr": 1606, "secondary_c9_c10_previous": 20111, "upper_pri_c6_c8_previous": 36826, "secondary_boy_c10_c11_current_fresh": 6696, "secondary_c9_c10_promotion_rate": 59.733479190492766, "pri_girl_c1_c5_dropout_rate": 5.794216840824902, "secondary_girl_c10_c11_current_fresh": 5317, "upper_pri_boy_c7_c9_current_fresh": 18461, "upper_pri_c6_c8_dropout_rate": 7.402378754141096, "pri_boy_c2_c6_current": 37048, "secondary_c10_c11_current_fresh": 12013, "pri_boy_c2_c6_current_fresh": 36425, "secondary_girl_c10_c11_current_rptr": 329, "upper_pri_girl_c6_c8_dropout_rate": 8.500357909806729, "pri_c1_c5_repitition_rate": 1.9390764916736107, "secondary_c9_c10_current_rptr": 2043, "location_name": "CHITTAURGARH", "pri_c2_c6_current_fresh": 69780, "upper_pri_c6_c8_current_rptr": 453, "upper_pri_boy_c7_c9_current_rptr": 1137, "upper_pri_boy_c6_c8_repitition_rate": 1.4953643704516, "upper_pri_girl_c7_c9_current_rptr": 469, "pri_girl_c1_c5_repitition_rate": 1.998673080112788, "pri_girl_c2_c6_current_rptr": 552, "upper_pri_boy_c6_c8_current_rptr": 300, "pri_boy_c1_c5_previous": 39429, "secondary_boy_c10_c11_current": 7417, "upper_pri_boy_c7_c9_current": 19598, "pri_boy_c1_c5_promotion_rate": 92.38124223287429, "upper_pri_c6_c8_promotion_rate": 91.3675120838538, "secondary_c10_c11_current": 13063, "secondary_girl_c9_c10_repitition_rate": 7.430264132313009, "secondary_boy_c9_c10_repitition_rate": 11.999333832958614, "secondary_girl_c9_c10_previous": 8102, "pri_boy_c2_c6_current_rptr": 623, "secondary_girl_c9_c10_current_rptr": 602, "pri_girl_c1_c5_previous": 36174, "secondary_c9_c10_dropout_rate": 30.107901148625132, "secondary_boy_c9_c10_current_rptr": 1441, "location_code": "0829", "pri_boy_c1_c5_current_rptr": 743, "secondary_girl_c9_c10_promotion_rate": 65.62577141446556, "upper_pri_boy_c6_c8_promotion_rate": 92.01973880968995, "secondary_boy_c9_c10_promotion_rate": 55.758181363977016, "upper_pri_girl_c6_c8_repitition_rate": 0.9126700071581961, "upper_pri_girl_c7_c9_current_fresh": 15186, "pri_girl_c1_c5_promotion_rate": 92.2071100790623, "pri_c1_c5_dropout_rate": 5.762998822798037, "item_id": 4, "item_name": "OBC", "pri_girl_c2_c6_current_fresh": 33355, "upper_pri_c6_c8_repitition_rate": 1.230109162005105, "pri_boy_c1_c5_dropout_rate": 5.734357959877248, "pri_c1_c5_previous": 75603, "upper_pri_girl_c7_c9_current": 15655, "pri_boy_c1_c5_repitition_rate": 1.884399807248472, "secondary_boy_c9_c10_dropout_rate": 32.24248480306437, "upper_pri_boy_c6_c8_previous": 20062, "upper_pri_c7_c9_current": 35253}, {"rpt_type": "D", "upper_pri_girl_c6_c8_promotion_rate": 89.29550314749555, "pri_c2_c6_current": 148147, "upper_pri_girl_c6_c8_current_rptr": 496, "pri_girl_c1_c5_current_rptr": 1745, "secondary_boy_c9_c10_previous": 23667, "pri_girl_c2_c6_current": 69510, "secondary_c9_c10_repitition_rate": 10.263820957462576, "pri_c1_c5_current_rptr": 3738, "pri_c1_c5_promotion_rate": 90.51951936979609, "secondary_c10_c11_current_rptr": 2134, "secondary_girl_c10_c11_current": 11509, "pri_c2_c6_current_rptr": 2903, "secondary_girl_c9_c10_dropout_rate": 27.689562890276537, "upper_pri_boy_c6_c8_dropout_rate": 7.965725166613773, "upper_pri_girl_c6_c8_previous": 33201, "secondary_boy_c10_c11_current_rptr": 1408, "upper_pri_c7_c9_current_fresh": 66713, "upper_pri_c7_c9_current_rptr": 3400, "secondary_c9_c10_previous": 40482, "upper_pri_c6_c8_previous": 74164, "secondary_boy_c10_c11_current_fresh": 13218, "secondary_c9_c10_promotion_rate": 59.2880786522405, "pri_girl_c1_c5_dropout_rate": 7.629121931249422, "secondary_girl_c10_c11_current_fresh": 10783, "upper_pri_boy_c7_c9_current_fresh": 37066, "upper_pri_c6_c8_dropout_rate": 8.523003074267839, "pri_boy_c2_c6_current": 78637, "secondary_c10_c11_current_fresh": 24001, "pri_boy_c2_c6_current_fresh": 77043, "secondary_girl_c10_c11_current_rptr": 726, "upper_pri_girl_c6_c8_dropout_rate": 9.210565946808831, "pri_c1_c5_repitition_rate": 2.329610609762178, "secondary_c9_c10_current_rptr": 4155, "location_name": "CHITTAURGARH", "pri_c2_c6_current_fresh": 145244, "upper_pri_c6_c8_current_rptr": 1130, "upper_pri_boy_c7_c9_current_rptr": 2237, "upper_pri_boy_c6_c8_repitition_rate": 1.547738202768352, "upper_pri_girl_c7_c9_current_rptr": 1163, "pri_girl_c1_c5_repitition_rate": 2.3044517517795122, "pri_girl_c2_c6_current_rptr": 1309, "upper_pri_boy_c6_c8_current_rptr": 634, "pri_boy_c1_c5_previous": 84733, "secondary_boy_c10_c11_current": 14626, "upper_pri_boy_c7_c9_current": 39303, "pri_boy_c1_c5_promotion_rate": 90.92443321964288, "upper_pri_c6_c8_promotion_rate": 89.95334663718246, "secondary_c10_c11_current": 26135, "secondary_girl_c9_c10_repitition_rate": 8.183169788878978, "secondary_boy_c9_c10_repitition_rate": 11.742088139603668, "secondary_girl_c9_c10_previous": 16815, "pri_boy_c2_c6_current_rptr": 1594, "secondary_girl_c9_c10_current_rptr": 1376, "pri_girl_c1_c5_previous": 75723, "secondary_c9_c10_dropout_rate": 30.448100390296922, "secondary_boy_c9_c10_current_rptr": 2779, "location_code": "0829", "pri_boy_c1_c5_current_rptr": 1993, "secondary_girl_c9_c10_promotion_rate": 64.12726732084448, "upper_pri_boy_c6_c8_promotion_rate": 90.48653663061788, "secondary_boy_c9_c10_promotion_rate": 55.84991760679427, "upper_pri_girl_c6_c8_repitition_rate": 1.4939309056956116, "upper_pri_girl_c7_c9_current_fresh": 29647, "pri_girl_c1_c5_promotion_rate": 90.06642631697106, "pri_c1_c5_dropout_rate": 7.150870020441741, "item_id": 6, "item_name": "Overall", "pri_girl_c2_c6_current_fresh": 68201, "upper_pri_c6_c8_repitition_rate": 1.5236502885497007, "pri_boy_c1_c5_dropout_rate": 6.723472554966778, "pri_c1_c5_previous": 160456, "upper_pri_girl_c7_c9_current": 30810, "pri_boy_c1_c5_repitition_rate": 2.352094225390344, "secondary_boy_c9_c10_dropout_rate": 32.40799425360206, "upper_pri_boy_c6_c8_previous": 40963, "upper_pri_c7_c9_current": 70113}], "staticFilter": null, "columnView": null, "columnDataType": null, "msData": null, "status": "1", "errorMessage": null, "jsonString": null, "yearList": ["2014-15", "2015-16", "2016-17", "2017-18", "2018-19"]}