{"columnName": ["rpt_type", "upper_pri_girl_c6_c8_promotion_rate", "pri_c2_c6_current", "upper_pri_girl_c6_c8_current_rptr", "pri_girl_c1_c5_current_rptr", "secondary_boy_c9_c10_previous", "pri_girl_c2_c6_current", "secondary_c9_c10_repitition_rate", "pri_c1_c5_current_rptr", "pri_c1_c5_promotion_rate", "secondary_c10_c11_current_rptr", "secondary_girl_c10_c11_current", "pri_c2_c6_current_rptr", "secondary_girl_c9_c10_dropout_rate", "upper_pri_boy_c6_c8_dropout_rate", "upper_pri_girl_c6_c8_previous", "secondary_boy_c10_c11_current_rptr", "upper_pri_c7_c9_current_fresh", "upper_pri_c7_c9_current_rptr", "secondary_c9_c10_previous", "upper_pri_c6_c8_previous", "secondary_boy_c10_c11_current_fresh", "secondary_c9_c10_promotion_rate", "pri_girl_c1_c5_dropout_rate", "secondary_girl_c10_c11_current_fresh", "upper_pri_boy_c7_c9_current_fresh", "upper_pri_c6_c8_dropout_rate", "pri_boy_c2_c6_current", "secondary_c10_c11_current_fresh", "pri_boy_c2_c6_current_fresh", "secondary_girl_c10_c11_current_rptr", "upper_pri_girl_c6_c8_dropout_rate", "pri_c1_c5_repitition_rate", "secondary_c9_c10_current_rptr", "location_name", "pri_c2_c6_current_fresh", "upper_pri_c6_c8_current_rptr", "upper_pri_boy_c7_c9_current_rptr", "upper_pri_boy_c6_c8_repitition_rate", "upper_pri_girl_c7_c9_current_rptr", "pri_girl_c1_c5_repitition_rate", "pri_girl_c2_c6_current_rptr", "upper_pri_boy_c6_c8_current_rptr", "pri_boy_c1_c5_previous", "secondary_boy_c10_c11_current", "upper_pri_boy_c7_c9_current", "pri_boy_c1_c5_promotion_rate", "upper_pri_c6_c8_promotion_rate", "secondary_c10_c11_current", "secondary_girl_c9_c10_repitition_rate", "secondary_boy_c9_c10_repitition_rate", "secondary_girl_c9_c10_previous", "pri_boy_c2_c6_current_rptr", "secondary_girl_c9_c10_current_rptr", "pri_girl_c1_c5_previous", "secondary_c9_c10_dropout_rate", "secondary_boy_c9_c10_current_rptr", "location_code", "pri_boy_c1_c5_current_rptr", "secondary_girl_c9_c10_promotion_rate", "upper_pri_boy_c6_c8_promotion_rate", "secondary_boy_c9_c10_promotion_rate", "upper_pri_girl_c6_c8_repitition_rate", "upper_pri_girl_c7_c9_current_fresh", "pri_girl_c1_c5_promotion_rate", "pri_c1_c5_dropout_rate", "item_id", "item_name", "pri_girl_c2_c6_current_fresh", "upper_pri_c6_c8_repitition_rate", "pri_boy_c1_c5_dropout_rate", "pri_c1_c5_previous", "upper_pri_girl_c7_c9_current", "pri_boy_c1_c5_repitition_rate", "secondary_boy_c9_c10_dropout_rate", "upper_pri_boy_c6_c8_previous", "upper_pri_c7_c9_current"], "rowValue": [{"rpt_type": "D", "upper_pri_girl_c6_c8_promotion_rate": 94.25978569866608, "pri_c2_c6_current": 37016, "upper_pri_girl_c6_c8_current_rptr": 3, "pri_girl_c1_c5_current_rptr": 6, "secondary_boy_c9_c10_previous": 7960, "pri_girl_c2_c6_current": 15680, "secondary_c9_c10_repitition_rate": 0.30364372469635625, "pri_c1_c5_current_rptr": 22, "pri_c1_c5_promotion_rate": 94.48076824845482, "secondary_c10_c11_current_rptr": 13, "secondary_girl_c10_c11_current": 5203, "pri_c2_c6_current_rptr": 23, "secondary_girl_c9_c10_dropout_rate": 11.35899182561308, "upper_pri_boy_c6_c8_dropout_rate": 2.458498023715415, "upper_pri_girl_c6_c8_previous": 9146, "secondary_boy_c10_c11_current_rptr": 12, "upper_pri_c7_c9_current_fresh": 20947, "upper_pri_c7_c9_current_rptr": 41, "secondary_c9_c10_previous": 13832, "upper_pri_c6_c8_previous": 21796, "secondary_boy_c10_c11_current_fresh": 7372, "secondary_c9_c10_promotion_rate": 90.90514748409485, "pri_girl_c1_c5_dropout_rate": 5.09592688978999, "secondary_girl_c10_c11_current_fresh": 5202, "upper_pri_boy_c7_c9_current_fresh": 12326, "upper_pri_c6_c8_dropout_rate": 3.8218021655349608, "pri_boy_c2_c6_current": 21336, "secondary_c10_c11_current_fresh": 12574, "pri_boy_c2_c6_current_fresh": 21318, "secondary_girl_c10_c11_current_rptr": 1, "upper_pri_girl_c6_c8_dropout_rate": 5.707413076754865, "pri_c1_c5_repitition_rate": 0.05618838432854881, "secondary_c9_c10_current_rptr": 42, "location_name": "FIROZPUR", "pri_c2_c6_current_fresh": 36993, "upper_pri_c6_c8_current_rptr": 16, "upper_pri_boy_c7_c9_current_rptr": 35, "upper_pri_boy_c6_c8_repitition_rate": 0.10276679841897234, "upper_pri_girl_c7_c9_current_rptr": 6, "pri_girl_c1_c5_repitition_rate": 0.036313018217030806, "pri_girl_c2_c6_current_rptr": 5, "upper_pri_boy_c6_c8_current_rptr": 13, "pri_boy_c1_c5_previous": 22631, "secondary_boy_c10_c11_current": 7384, "upper_pri_boy_c7_c9_current": 12361, "pri_boy_c1_c5_promotion_rate": 94.19822367548937, "upper_pri_c6_c8_promotion_rate": 96.10478986970087, "secondary_c10_c11_current": 12587, "secondary_girl_c9_c10_repitition_rate": 0.05108991825613079, "secondary_boy_c9_c10_repitition_rate": 0.4899497487437186, "secondary_girl_c9_c10_previous": 5872, "pri_boy_c2_c6_current_rptr": 18, "secondary_girl_c9_c10_current_rptr": 3, "pri_girl_c1_c5_previous": 16523, "secondary_c9_c10_dropout_rate": 8.791208791208792, "secondary_boy_c9_c10_current_rptr": 39, "location_code": "0311", "pri_boy_c1_c5_current_rptr": 16, "secondary_girl_c9_c10_promotion_rate": 88.58991825613079, "upper_pri_boy_c6_c8_promotion_rate": 97.43873517786561, "secondary_boy_c9_c10_promotion_rate": 92.61306532663316, "upper_pri_girl_c6_c8_repitition_rate": 0.03280122457905095, "upper_pri_girl_c7_c9_current_fresh": 8621, "pri_girl_c1_c5_promotion_rate": 94.86776009199298, "pri_c1_c5_dropout_rate": 5.463043367216632, "item_id": 1, "item_name": "General", "pri_girl_c2_c6_current_fresh": 15675, "upper_pri_c6_c8_repitition_rate": 0.07340796476417691, "pri_boy_c1_c5_dropout_rate": 5.731076841500596, "pri_c1_c5_previous": 39154, "upper_pri_girl_c7_c9_current": 8627, "pri_boy_c1_c5_repitition_rate": 0.07069948301003048, "secondary_boy_c9_c10_dropout_rate": 6.896984924623116, "upper_pri_boy_c6_c8_previous": 12650, "upper_pri_c7_c9_current": 20988}, {"rpt_type": "D", "upper_pri_girl_c6_c8_promotion_rate": 97.95508490049298, "pri_c2_c6_current": 47666, "upper_pri_girl_c6_c8_current_rptr": 0, "pri_girl_c1_c5_current_rptr": 9, "secondary_boy_c9_c10_previous": 6642, "pri_girl_c2_c6_current": 22565, "secondary_c9_c10_repitition_rate": 1.5038240096244737, "pri_c1_c5_current_rptr": 25, "pri_c1_c5_promotion_rate": 98.64806111674706, "secondary_c10_c11_current_rptr": 54, "secondary_girl_c10_c11_current": 4523, "pri_c2_c6_current_rptr": 18, "secondary_girl_c9_c10_dropout_rate": 8.76876876876877, "upper_pri_boy_c6_c8_dropout_rate": 5.525525525525525, "upper_pri_girl_c6_c8_previous": 10954, "secondary_boy_c10_c11_current_rptr": 34, "upper_pri_c7_c9_current_fresh": 23313, "upper_pri_c7_c9_current_rptr": 130, "secondary_c9_c10_previous": 11637, "upper_pri_c6_c8_previous": 24274, "secondary_boy_c10_c11_current_fresh": 5441, "secondary_c9_c10_promotion_rate": 85.4515768668901, "pri_girl_c1_c5_dropout_rate": 1.5702010729707332, "secondary_girl_c10_c11_current_fresh": 4503, "upper_pri_boy_c7_c9_current_fresh": 12583, "upper_pri_c6_c8_dropout_rate": 3.954848809425723, "pri_boy_c2_c6_current": 25101, "secondary_c10_c11_current_fresh": 9944, "pri_boy_c2_c6_current_fresh": 25090, "secondary_girl_c10_c11_current_rptr": 20, "upper_pri_girl_c6_c8_dropout_rate": 2.0449150995070293, "pri_c1_c5_repitition_rate": 0.05175876275853502, "secondary_c9_c10_current_rptr": 175, "location_name": "FIROZPUR", "pri_c2_c6_current_fresh": 47648, "upper_pri_c6_c8_current_rptr": 1, "upper_pri_boy_c7_c9_current_rptr": 94, "upper_pri_boy_c6_c8_repitition_rate": 0.0075075075075075074, "upper_pri_girl_c7_c9_current_rptr": 36, "pri_girl_c1_c5_repitition_rate": 0.03925502682426833, "pri_girl_c2_c6_current_rptr": 7, "upper_pri_boy_c6_c8_current_rptr": 1, "pri_boy_c1_c5_previous": 25374, "secondary_boy_c10_c11_current": 5475, "upper_pri_boy_c7_c9_current": 12677, "pri_boy_c1_c5_promotion_rate": 98.88074406873177, "upper_pri_c6_c8_promotion_rate": 96.0410315563978, "secondary_c10_c11_current": 9998, "secondary_girl_c9_c10_repitition_rate": 1.0810810810810811, "secondary_boy_c9_c10_repitition_rate": 1.8217404396266186, "secondary_girl_c9_c10_previous": 4995, "pri_boy_c2_c6_current_rptr": 11, "secondary_girl_c9_c10_current_rptr": 54, "pri_girl_c1_c5_previous": 22927, "secondary_c9_c10_dropout_rate": 13.044599123485435, "secondary_boy_c9_c10_current_rptr": 121, "location_code": "0311", "pri_boy_c1_c5_current_rptr": 16, "secondary_girl_c9_c10_promotion_rate": 90.15015015015015, "upper_pri_boy_c6_c8_promotion_rate": 94.46696696696696, "secondary_boy_c9_c10_promotion_rate": 81.91809695874737, "upper_pri_girl_c6_c8_repitition_rate": 0.0, "upper_pri_girl_c7_c9_current_fresh": 10730, "pri_girl_c1_c5_promotion_rate": 98.390543900205, "pri_c1_c5_dropout_rate": 1.3001801204943997, "item_id": 2, "item_name": "SC", "pri_girl_c2_c6_current_fresh": 22558, "upper_pri_c6_c8_repitition_rate": 0.004119634176485128, "pri_boy_c1_c5_dropout_rate": 1.0561992590841018, "pri_c1_c5_previous": 48301, "upper_pri_girl_c7_c9_current": 10766, "pri_boy_c1_c5_repitition_rate": 0.06305667218412549, "secondary_boy_c9_c10_dropout_rate": 16.260162601626018, "upper_pri_boy_c6_c8_previous": 13320, "upper_pri_c7_c9_current": 23443}, {"rpt_type": "D", "upper_pri_girl_c6_c8_promotion_rate": 68.75, "pri_c2_c6_current": 107, "upper_pri_girl_c6_c8_current_rptr": 0, "pri_girl_c1_c5_current_rptr": 0, "secondary_boy_c9_c10_previous": 14, "pri_girl_c2_c6_current": 47, "secondary_c9_c10_repitition_rate": 0.0, "pri_c1_c5_current_rptr": 0, "pri_c1_c5_promotion_rate": 53.5, "secondary_c10_c11_current_rptr": 0, "secondary_girl_c10_c11_current": 6, "pri_c2_c6_current_rptr": 0, "secondary_girl_c9_c10_dropout_rate": 40.0, "upper_pri_boy_c6_c8_dropout_rate": 31.57894736842105, "upper_pri_girl_c6_c8_previous": 16, "secondary_boy_c10_c11_current_rptr": 0, "upper_pri_c7_c9_current_fresh": 24, "upper_pri_c7_c9_current_rptr": 0, "secondary_c9_c10_previous": 24, "upper_pri_c6_c8_previous": 35, "secondary_boy_c10_c11_current_fresh": 15, "secondary_c9_c10_promotion_rate": 87.5, "pri_girl_c1_c5_dropout_rate": 53.0, "secondary_girl_c10_c11_current_fresh": 6, "upper_pri_boy_c7_c9_current_fresh": 13, "upper_pri_c6_c8_dropout_rate": 31.428571428571427, "pri_boy_c2_c6_current": 60, "secondary_c10_c11_current_fresh": 21, "pri_boy_c2_c6_current_fresh": 60, "secondary_girl_c10_c11_current_rptr": 0, "upper_pri_girl_c6_c8_dropout_rate": 31.25, "pri_c1_c5_repitition_rate": 0.0, "secondary_c9_c10_current_rptr": 0, "location_name": "FIROZPUR", "pri_c2_c6_current_fresh": 107, "upper_pri_c6_c8_current_rptr": 0, "upper_pri_boy_c7_c9_current_rptr": 0, "upper_pri_boy_c6_c8_repitition_rate": 0.0, "upper_pri_girl_c7_c9_current_rptr": 0, "pri_girl_c1_c5_repitition_rate": 0.0, "pri_girl_c2_c6_current_rptr": 0, "upper_pri_boy_c6_c8_current_rptr": 0, "pri_boy_c1_c5_previous": 100, "secondary_boy_c10_c11_current": 15, "upper_pri_boy_c7_c9_current": 13, "pri_boy_c1_c5_promotion_rate": 60.0, "upper_pri_c6_c8_promotion_rate": 68.57142857142857, "secondary_c10_c11_current": 21, "secondary_girl_c9_c10_repitition_rate": 0.0, "secondary_boy_c9_c10_repitition_rate": 0.0, "secondary_girl_c9_c10_previous": 10, "pri_boy_c2_c6_current_rptr": 0, "secondary_girl_c9_c10_current_rptr": 0, "pri_girl_c1_c5_previous": 100, "secondary_c9_c10_dropout_rate": 12.5, "secondary_boy_c9_c10_current_rptr": 0, "location_code": "0311", "pri_boy_c1_c5_current_rptr": 0, "secondary_girl_c9_c10_promotion_rate": 60.0, "upper_pri_boy_c6_c8_promotion_rate": 68.42105263157895, "secondary_boy_c9_c10_promotion_rate": 100.0, "upper_pri_girl_c6_c8_repitition_rate": 0.0, "upper_pri_girl_c7_c9_current_fresh": 11, "pri_girl_c1_c5_promotion_rate": 47.0, "pri_c1_c5_dropout_rate": 46.5, "item_id": 3, "item_name": "ST", "pri_girl_c2_c6_current_fresh": 47, "upper_pri_c6_c8_repitition_rate": 0.0, "pri_boy_c1_c5_dropout_rate": 40.0, "pri_c1_c5_previous": 200, "upper_pri_girl_c7_c9_current": 11, "pri_boy_c1_c5_repitition_rate": 0.0, "secondary_boy_c9_c10_dropout_rate": 0.0, "upper_pri_boy_c6_c8_previous": 19, "upper_pri_c7_c9_current": 24}, {"rpt_type": "D", "upper_pri_girl_c6_c8_promotion_rate": 100.0, "pri_c2_c6_current": 6853, "upper_pri_girl_c6_c8_current_rptr": 0, "pri_girl_c1_c5_current_rptr": 0, "secondary_boy_c9_c10_previous": 1645, "pri_girl_c2_c6_current": 3043, "secondary_c9_c10_repitition_rate": 0.6243496357960457, "pri_c1_c5_current_rptr": 2, "pri_c1_c5_promotion_rate": 99.2035910802201, "secondary_c10_c11_current_rptr": 6, "secondary_girl_c10_c11_current": 1227, "pri_c2_c6_current_rptr": 2, "secondary_girl_c9_c10_dropout_rate": 0.6462035541195477, "upper_pri_boy_c6_c8_dropout_rate": 5.041354864119732, "upper_pri_girl_c6_c8_previous": 1999, "secondary_boy_c10_c11_current_rptr": 5, "upper_pri_c7_c9_current_fresh": 4484, "upper_pri_c7_c9_current_rptr": 14, "secondary_c9_c10_previous": 2883, "upper_pri_c6_c8_previous": 4538, "secondary_boy_c10_c11_current_fresh": 1446, "secondary_c9_c10_promotion_rate": 92.68123482483524, "pri_girl_c1_c5_dropout_rate": 0.0, "secondary_girl_c10_c11_current_fresh": 1226, "upper_pri_boy_c7_c9_current_fresh": 2408, "upper_pri_c6_c8_dropout_rate": 1.123843102688409, "pri_boy_c2_c6_current": 3810, "secondary_c10_c11_current_fresh": 2672, "pri_boy_c2_c6_current_fresh": 3808, "secondary_girl_c10_c11_current_rptr": 1, "upper_pri_girl_c6_c8_dropout_rate": 0.0, "pri_c1_c5_repitition_rate": 0.028960324355632783, "secondary_c9_c10_current_rptr": 18, "location_name": "FIROZPUR", "pri_c2_c6_current_fresh": 6851, "upper_pri_c6_c8_current_rptr": 3, "upper_pri_boy_c7_c9_current_rptr": 11, "upper_pri_boy_c6_c8_repitition_rate": 0.11815675462780623, "upper_pri_girl_c7_c9_current_rptr": 3, "pri_girl_c1_c5_repitition_rate": 0.0, "pri_girl_c2_c6_current_rptr": 0, "upper_pri_boy_c6_c8_current_rptr": 3, "pri_boy_c1_c5_previous": 3945, "secondary_boy_c10_c11_current": 1451, "upper_pri_boy_c7_c9_current": 2419, "pri_boy_c1_c5_promotion_rate": 96.52724968314322, "upper_pri_c6_c8_promotion_rate": 98.81004847950639, "secondary_c10_c11_current": 2678, "secondary_girl_c9_c10_repitition_rate": 0.32310177705977383, "secondary_boy_c9_c10_repitition_rate": 0.851063829787234, "secondary_girl_c9_c10_previous": 1238, "pri_boy_c2_c6_current_rptr": 2, "secondary_girl_c9_c10_current_rptr": 4, "pri_girl_c1_c5_previous": 2961, "secondary_c9_c10_dropout_rate": 6.6944155393687135, "secondary_boy_c9_c10_current_rptr": 14, "location_code": "0311", "pri_boy_c1_c5_current_rptr": 2, "secondary_girl_c9_c10_promotion_rate": 99.03069466882067, "upper_pri_boy_c6_c8_promotion_rate": 94.84048838125246, "secondary_boy_c9_c10_promotion_rate": 87.90273556231003, "upper_pri_girl_c6_c8_repitition_rate": 0.0, "upper_pri_girl_c7_c9_current_fresh": 2076, "pri_girl_c1_c5_promotion_rate": 100.0, "pri_c1_c5_dropout_rate": 0.7674485954242687, "item_id": 4, "item_name": "OBC", "pri_girl_c2_c6_current_fresh": 3043, "upper_pri_c6_c8_repitition_rate": 0.06610841780520053, "pri_boy_c1_c5_dropout_rate": 3.4220532319391634, "pri_c1_c5_previous": 6906, "upper_pri_girl_c7_c9_current": 2079, "pri_boy_c1_c5_repitition_rate": 0.050697084917617236, "secondary_boy_c9_c10_dropout_rate": 11.246200607902736, "upper_pri_boy_c6_c8_previous": 2539, "upper_pri_c7_c9_current": 4498}, {"rpt_type": "D", "upper_pri_girl_c6_c8_promotion_rate": 96.93872936920643, "pri_c2_c6_current": 91642, "upper_pri_girl_c6_c8_current_rptr": 3, "pri_girl_c1_c5_current_rptr": 15, "secondary_boy_c9_c10_previous": 16261, "pri_girl_c2_c6_current": 41335, "secondary_c9_c10_repitition_rate": 0.8281646461798703, "pri_c1_c5_current_rptr": 49, "pri_c1_c5_promotion_rate": 96.86763041846004, "secondary_c10_c11_current_rptr": 73, "secondary_girl_c10_c11_current": 10959, "pri_c2_c6_current_rptr": 43, "secondary_girl_c9_c10_dropout_rate": 9.219975237309121, "upper_pri_boy_c6_c8_dropout_rate": 4.139792484576557, "upper_pri_girl_c6_c8_previous": 22115, "secondary_boy_c10_c11_current_rptr": 51, "upper_pri_c7_c9_current_fresh": 48768, "upper_pri_c7_c9_current_rptr": 185, "secondary_c9_c10_previous": 28376, "upper_pri_c6_c8_previous": 50643, "secondary_boy_c10_c11_current_fresh": 14274, "secondary_c9_c10_promotion_rate": 88.84620806315196, "pri_girl_c1_c5_dropout_rate": 2.7592858319023312, "secondary_girl_c10_c11_current_fresh": 10937, "upper_pri_boy_c7_c9_current_fresh": 27330, "upper_pri_c6_c8_dropout_rate": 3.6628951681377484, "pri_boy_c2_c6_current": 50307, "secondary_c10_c11_current_fresh": 25211, "pri_boy_c2_c6_current_fresh": 50276, "secondary_girl_c10_c11_current_rptr": 22, "upper_pri_girl_c6_c8_dropout_rate": 3.0477051774813475, "pri_c1_c5_repitition_rate": 0.05181840293567115, "secondary_c9_c10_current_rptr": 235, "location_name": "FIROZPUR", "pri_c2_c6_current_fresh": 91599, "upper_pri_c6_c8_current_rptr": 20, "upper_pri_boy_c7_c9_current_rptr": 140, "upper_pri_boy_c6_c8_repitition_rate": 0.05959057767807067, "upper_pri_girl_c7_c9_current_rptr": 45, "pri_girl_c1_c5_repitition_rate": 0.03528498506268966, "pri_girl_c2_c6_current_rptr": 12, "upper_pri_boy_c6_c8_current_rptr": 17, "pri_boy_c1_c5_previous": 52050, "secondary_boy_c10_c11_current": 14325, "upper_pri_boy_c7_c9_current": 27470, "pri_boy_c1_c5_promotion_rate": 96.59173871277618, "upper_pri_c6_c8_promotion_rate": 96.29761270066939, "secondary_c10_c11_current": 25284, "secondary_girl_c9_c10_repitition_rate": 0.5035080478745357, "secondary_boy_c9_c10_repitition_rate": 1.0700448926880266, "secondary_girl_c9_c10_previous": 12115, "pri_boy_c2_c6_current_rptr": 31, "secondary_girl_c9_c10_current_rptr": 61, "pri_girl_c1_c5_previous": 42511, "secondary_c9_c10_dropout_rate": 10.32562729066817, "secondary_boy_c9_c10_current_rptr": 174, "location_code": "0311", "pri_boy_c1_c5_current_rptr": 34, "secondary_girl_c9_c10_promotion_rate": 90.27651671481634, "upper_pri_boy_c6_c8_promotion_rate": 95.80061693774537, "secondary_boy_c9_c10_promotion_rate": 87.78057930016604, "upper_pri_girl_c6_c8_repitition_rate": 0.013565453312231517, "upper_pri_girl_c7_c9_current_fresh": 21438, "pri_girl_c1_c5_promotion_rate": 97.20542918303498, "pri_c1_c5_dropout_rate": 3.080551178604287, "item_id": 6, "item_name": "Overall", "pri_girl_c2_c6_current_fresh": 41323, "upper_pri_c6_c8_repitition_rate": 0.039492131192859825, "pri_boy_c1_c5_dropout_rate": 3.3429394812680115, "pri_c1_c5_previous": 94561, "upper_pri_girl_c7_c9_current": 21483, "pri_boy_c1_c5_repitition_rate": 0.06532180595581172, "secondary_boy_c9_c10_dropout_rate": 11.149375807145931, "upper_pri_boy_c6_c8_previous": 28528, "upper_pri_c7_c9_current": 48953}], "staticFilter": null, "columnView": null, "columnDataType": null, "msData": null, "status": "1", "errorMessage": null, "jsonString": null, "yearList": ["2014-15", "2015-16", "2016-17", "2017-18", "2018-19"]}